[{"title":"<โปรโมชัน> ชุดเซตคุกกี้เดลี่ S&P (กล่องกิ๊ฟเซต 4 กระปุก)","description":"พิเศษ! 235.- จากปกติ 275.- \n(คุ้กกี้ 4 กระปุก ราคาพิเศษ)","imageSrc":"https://d1sag4ddilekf6.cloudfront.net/compressed_webp/items/THITE20230810091931061045/detail/e03e4e6cb2d64c158ef99756692e4a33_1692273619691772781.webp","price":"235"},{"title":"ข้าวพร้อมกับ3อย่าง + เครื่องดื่ม 1 แก้ว GrabBox 🍱","description":"","imageSrc":"https://d1sag4ddilekf6.cloudfront.net/compressed_webp/items/THITE20230628103945076637/detail/183044736a6c4159bb4fc06ae08f0a7e_1687948785232576163.webp","price":"219"},{"title":"<โปรโมชัน> น้ำส้มวาเลนเซีย(6กล่อง)","description":"พิเศษ! 95.- จากปกติ 114.- \n(น้ำผลไม้ UHT 6 กล่อง ราคาพิเศษ)","imageSrc":"https://d1sag4ddilekf6.cloudfront.net/compressed_webp/items/THITE20230810091931139570/detail/85ae35e9336c44c694146adbc307aa6a_1692273619855201227.webp","price":"95"},{"title":"<โปรโมชัน> น้ำแอปเปิ้ลผสมน้ำทับทิม(6กล่อง)","description":"พิเศษ! 95.- จากปกติ 114.- \n(น้ำผลไม้ UHT 6 กล่อง ราคาพิเศษ)","imageSrc":"https://d1sag4ddilekf6.cloudfront.net/compressed_webp/items/THITE20230810091931167030/detail/1bae01237f1a47bf8ef6ffec17ba9229_1692273619940933374.webp","price":"95"},{"title":"<โปรโมชัน> น้ำนมข้าวโพด(6กล่อง)","description":"พิเศษ! 95.- จากปกติ 114.- \n(น้ำผลไม้ UHT 6 กล่อง ราคาพิเศษ)","imageSrc":"https://d1sag4ddilekf6.cloudfront.net/compressed_webp/items/THITE20230810091931202668/detail/d0dc9f5e62a6474e850ed2e9bb3589d6_1692273619838871062.webp","price":"95"},{"title":"<โปรโมชัน> น้ำองุ่นแดง(6กล่อง)","description":"พิเศษ! 95.- จากปกติ 114.- \n(น้ำผลไม้ UHT 6 กล่อง ราคาพิเศษ)","imageSrc":"https://d1sag4ddilekf6.cloudfront.net/compressed_webp/items/THITE20230810091931247401/detail/98e9d06037514508afe9fc43a4721b67_1692273619946046166.webp","price":"95"},{"title":"<โปรโมชัน> ชุดเซตข้าวเกรียบ 2 กระป๋อง","description":"พิเศษ! 150.- จากปกติ 176.- \n(ชุดข้าวเกรียบ 2 กระป๋อง ราคาพิเศษ)","imageSrc":"https://d1sag4ddilekf6.cloudfront.net/compressed_webp/items/THITE20230810091931288387/detail/5d09146006974133b1a448c1ab82ba44_1692273619917830821.webp","price":"150"},{"title":"<โปรโมชัน> ชุดเซตทองม้วน 2 กล่อง","description":"พิเศษ! 200.- จากปกติ 250.- \n(ชุดทองม้วน 2 กล่อง ราคาพิเศษ)","imageSrc":"https://d1sag4ddilekf6.cloudfront.net/compressed_webp/items/THITE20230810091931346053/detail/2b680d045f944a3dabf3829fba31e091_1692273619931179867.webp","price":"200"},{"title":"<โปรโมชัน> ชุดเซตขนมขาไก่เนยสด 2 กระปุก","description":"พิเศษ! 108.- จากปกติ 136.- \n(ชุดขาไก่เนยสด 2 กระปุก ราคาพิเศษ)","imageSrc":"https://d1sag4ddilekf6.cloudfront.net/compressed_webp/items/THITE20230810091931394491/detail/c8ee31024ef949d5afcd2c584013d27e_1692273620233793505.webp","price":"108"},{"title":"<โปรโมชัน> ชุดเซตฟรุตพายสับปะรด 4 กล่อง","description":"พิเศษ! 200.- จากปกติ 232.- \n(ชุดฟรุตพายสับปะรด 4 กล่อง ราคาพิเศษ)","imageSrc":"https://d1sag4ddilekf6.cloudfront.net/compressed_webp/items/THITE20230810091932023639/detail/93ea166d45154d84bf8d61d1f37d7961_1692273620029908274.webp","price":"200"},{"title":"<โปรโมชัน> ชุดเซตคุกกี้ผสมธัญพืช 2 กระปุก","description":"พิเศษ! 125.- จากปกติ 150.- \n(ชุดคุกกี้ธัญพืช 2 กระปุก ราคาพิเศษ)","imageSrc":"https://d1sag4ddilekf6.cloudfront.net/compressed_webp/items/THITE20230810091932082997/detail/8bc33ec2c80546d9808e31ab4b373e7f_1692273619718421518.webp","price":"125"},{"title":"<โปรโมชัน> ชุดพายกรอบแท่ง 2 กระปุก","description":"พิเศษ! 100.- จากปกติ 116.- \n(ชุดพายกรอบแท่ง 2 กระปุก ราคาพิเศษ)","imageSrc":"https://d1sag4ddilekf6.cloudfront.net/compressed_webp/items/THITE20230810091932141571/detail/7988d9e47e4242439e4886d901a83736_1692273619705438286.webp","price":"100"},{"title":"<โปรโมชัน> ชุดเซตพัฟเค้กสอดไส้ครีมกลิ่นส้ม 2 กล่อง","description":"พิเศษ! 100.- จากปกติ 110.- \n(ชุดพัฟเค้กสอดไส้ครีมกลิ่นส้ม 2 กล่อง ราคาพิเศษ)","imageSrc":"https://d1sag4ddilekf6.cloudfront.net/compressed_webp/items/THITE20230810091932181397/detail/6b5c321244624971a999f0d63798c363_1692273619843685029.webp","price":"100"},{"title":"<โปรโมชัน> ขนมจีบกุ้ง","description":"พิเศษ! 80.- จากปกติ 98.- \n(ขนมจีบกุ้ง 1 กล่อง ราคาพิเศษ)","imageSrc":"https://d1sag4ddilekf6.cloudfront.net/compressed_webp/items/THITE20230810091932211430/detail/f7716be2babf48759e9fcd5b003aebc0_1692273619849827528.webp","price":"80"},{"title":"<โปรโมชัน> ชุดเซตคุกกี้เดลี่ 2 กระปุก","description":"พิเศษ! 110.- จากปกติ 130.- (คุ้กกี้เดลี่ 2 กระปุก ราคาพิเศษ)","imageSrc":"https://d1sag4ddilekf6.cloudfront.net/compressed_webp/items/THITE20230831170036011463/detail/d69f69768c2e48c2a39a9b3d2bebc990_1693501236170096879.webp","price":"110"},{"title":"<โปรโมชัน> ขนมปังเนยสด 4 ชิ้น","description":"พิเศษ! 59.- จากปกติ 72.- (ขนมปังเนยสด 4 ชิ้น )","imageSrc":"https://d1sag4ddilekf6.cloudfront.net/compressed_webp/items/THITE20230831170036079285/detail/a9683935085e45058c9cd863ac405ef1_1693501236522399129.webp","price":"59"},{"title":"<โปรโมชัน> ครัวซองท์เนยสด 3 ชิ้น","description":"พิเศษ! 100.- จากปกติราคา 114.- ครัวซองท์เนยสด 3 ชิ้น","imageSrc":"https://d1sag4ddilekf6.cloudfront.net/compressed_webp/items/THITE20230831170036111586/detail/0b0b4e66cc114c57ac6332d8d4a652cf_1693501236812672566.webp","price":"100"},{"title":"<โปรโมชัน> เค้กนุ่ม 2 กล่อง (คละรสได้)","description":"เค้กนุ่ม 2 กล่อง (คละรสได้) \nพิเศษ! 200.- จากปกติ 250.-","imageSrc":"https://d1sag4ddilekf6.cloudfront.net/compressed_webp/items/THITE20230912052620039228/detail/f0720fa0b6404639a137a5e350621efc_1694767478211240048.webp","price":"200"},{"title":"<โปรโมชัน> คุกกี้ธัญพืช 1 กระปุก และ คุกกี้เดลี่ 1 กระปุก","description":"พิเศษ! 110.- จากปกติ 140.- \n(คุกกี้ธัญพืช 1 กระปุก \nและ คุกกี้เดลี่ 1 กระปุก\nราคาพิเศษ)","imageSrc":"https://d1sag4ddilekf6.cloudfront.net/compressed_webp/items/THITE20230912052620064498/detail/dc05cb46270d49f68687698ff22b07d2_1694767527218806455.webp","price":"110"},{"title":"<โปรโมชัน> ขนมไหว้พระจันทร์ (ซื้อ 4 ชิ้น รับฟรี 1 ชิ้น)","description":"พิเศษ! 420.- \nจากปกติ 525.- \n(ซื้อขนมไหว้พระจันทร์ 4 ชิ้น รับฟรี 1 ชิ้น)","imageSrc":"https://d1sag4ddilekf6.cloudfront.net/compressed_webp/items/THITE20230731071628040521/detail/ae09d4df80b244c184ac9b18802e6d9d_1693205461375296894.webp","price":"420"},{"title":"<โปรโมชั่น> ชุดอาหารจานเดียวครบเครื่อง","description":"พิเศษ! จากปกติราคา 264.- (อาหารจานเดียว 1 เมนู + เครื่องดื่ม 1 เมนู)","imageSrc":"https://d1sag4ddilekf6.cloudfront.net/compressed_webp/items/THITE20230731071629079093/detail/1e7ac4aad4374c73bf21d96f5994a384_1690787789620600889.webp","price":"198"},{"title":"<โปรโมชัน> ชุดปลากะพงสุดคุ้ม (ลาบไก่ + ผัดแขนง)","description":"พิเศษ! จากปกติราคา 738.- (ปลากะพงทอด + ลาบไก่-มันทอดกรอบ + ผัดแขนงกะหล่ำน้ำมันหอย)","imageSrc":"https://d1sag4ddilekf6.cloudfront.net/compressed_webp/items/THITE20230531171150035164/detail/1a40b217a0e94ac49f07175f7f6aca1c_1690821020575611514.webp","price":"625"},{"title":"<โปรโมชัน> BlueCup ซื้อ 1 แถม 1 (เมนูปั่น แถม เย็น)","description":"พิเศษ จากปกติสูงสุดราคา 263.-","imageSrc":"https://d1sag4ddilekf6.cloudfront.net/compressed_webp/items/THITE20230423114546650313/detail/2db56ee74afb42ab861e2428f4a22961_1687948782516850175.webp","price":"158"},{"title":"<โปรโมชัน> ลด35% ข้าวคลุกกะปิ+ข้าวผัดกุ้ง+น้ำ2","description":"ข้าวคลุกกะปิ + ข้าวผัดกุ้ง + ชา + กาแฟ","imageSrc":"https://d1sag4ddilekf6.cloudfront.net/compressed_webp/items/THITE20230423114545018833/detail/bc4febc00bfc49c29e7ef7e35dfca9f4_1684669638619963416.webp","price":"298"},{"title":"<โปรโมชัน> ลด30% ชุดอาหารจานเดียว 3 เมนู","description":"เลือก 3 จาก 5 (ข้าวหมูสไลซ์ทอดกระเทียมพริกไทยไข่นุ่ม / ข้าวคลุกกะปิ / ข้าวผัดกุ้ง / ข้าวหน้าไก่ราชวงศ์ / ข้าวผัดซาร์ดีน –ไข่ดาวกรอบ)","imageSrc":"https://d1sag4ddilekf6.cloudfront.net/compressed_webp/items/THITE20230521114951012876/detail/c349e94bb30146b89edd7272fedc5b0e_1692005641472725385.webp","price":"319"},{"title":"<โปรโมชัน> ชุดกับข้าวอร่อยคุ้ม","description":"พิเศษ! จากปกติราคา 445.-\n(แกงส้มชะอมกุ้งสด + ไข่ลูกสะใภ้ + ทอดมันปลาอินทรีย์)","imageSrc":"https://d1sag4ddilekf6.cloudfront.net/compressed_webp/items/THITE20230731071630027824/detail/329064f581ae42e7bdb515f82ae8e942_1690787790077224312.webp","price":"345"},{"title":"<โปรโมชัน> (ชุดอิสานสุดคุ้ม) ส้มตำไทย-ข้าวเหนียวคีนัว + เครื่องเคียง","description":"ชุดอาหารอีสาน ส้มตำไทย-ข้าวเหนียวคีนัว + เลือกเครื่องเคียงได้ตามใจ 1 รายการ","imageSrc":"https://d1sag4ddilekf6.cloudfront.net/compressed_webp/items/THITE20230628103945137355/detail/3fccf8b25db1409d91296c6ba757ebf8_1687948785542156936.webp","price":"199"},{"title":"<โปรโมชัน> (ชุดอิสานสุดคุ้ม) ลาบไก่-ข้าวเหนียวคีนัว + เครื่องเคียง","description":"ชุดอาหารอีสาน ลาบไก่-ข้าวเหนียวคีนัว + เลือกเครื่องเคียงได้ตามใจ 1 รายการ","imageSrc":"https://d1sag4ddilekf6.cloudfront.net/compressed_webp/items/THITE20230628103945179219/detail/728fa9bc4b4049f8bec7583c24d9b606_1687948785795418846.webp","price":"199"},{"title":"<โปรโมชัน> ข้าวพร้อมกับข้าว 2 อย่าง (ซื้อ 5 ฟรี 1)","description":"","imageSrc":"https://d1sag4ddilekf6.cloudfront.net/compressed_webp/items/THITE20230315072021018821/detail/1f00f700e5834815b21555a1647d0a4b_1678865204382279774.webp","price":"645"},{"title":"เค้กทริปเปิลเฟลเวอร์ 1 ปอนด์","description":"","imageSrc":"https://d1sag4ddilekf6.cloudfront.net/compressed_webp/items/THITE20230802144026013588/detail/2b3fc6f1f7414acdaba76533b52db319_1690987199516745126.webp","price":"435"},{"title":"VIP ข้าวหน้าแซลมอนย่างซีอิ้ว + บัวลอยมันม่วง","description":"VIP Salmon Teriyaki on Rice and Purple Sweet Potato Pearls in Coconut Cream","imageSrc":"https://d1sag4ddilekf6.cloudfront.net/compressed_webp/items/THITE20210531153646241890/detail/3edb1278cf0a4d2a9efe5039717e6fb9_1661167200419905600.webp","price":"285"},{"title":"VIP ข้าวกะเพราไก่ไข่นุ่ม+ปอเปี๊ยะญวนทอด+บัวลอยเผือก","description":"VIP Omelet on Rice w/ Spicy Chicken Basil + Fried Spring Rolls + Taro Balls in Coconut Cream","imageSrc":"https://d1sag4ddilekf6.cloudfront.net/compressed_webp/items/THITE20210531153646374012/detail/45866e2df76e4c6fa6ef7b79f05f41b9_1661167200422150328.webp","price":"255"},{"title":"VIP ชุดข้าวแกงเขียวหวานไก่ไข่นุ่ม + ขนมจีบกุ้ง + เค้กกล้วยหอม","description":"VIP Soft Omelet on Rice w/Chicken Green Curry + Shrimp Roe Dimsum + Banana Cake","imageSrc":"https://d1sag4ddilekf6.cloudfront.net/compressed_webp/items/THITE20210531153647140792/detail/1b2f7530a6494201a8251fa924f8e76a_1661167200429976968.webp","price":"215"},{"title":"VIP ชุดข้าวผัดคีนัว-แซลมอนทอดซอสน้ำปลา + สาคูถั่วดำมะพร้าวอ่อน","description":"VIP Quinoa Fried Rice w/ Savoury Salmon +  Sago & Black Bean in Coconut Cream","imageSrc":"https://d1sag4ddilekf6.cloudfront.net/compressed_webp/items/THITE20210531153646342170/detail/96158720d00f49acac30296d40a0e7d7_1661167200452662340.webp","price":"305"},{"title":"VIP ข้าวผัดน้ำพริกกุ้งสด+ปีกไก่ทอดสมุนไพร+กล้วยไข่บวดชี","description":"VIP Prawns Sweet Pork Fried Rice w/ Chilli Sauce+Deep - Fried Chicken Wings+Sweet Banana in Coconut Cream","imageSrc":"https://d1sag4ddilekf6.cloudfront.net/compressed_webp/items/THITE20220420112936016858/detail/53853f365cb04a06b13134c87ac65915_1661167200433661194.webp","price":"275"},{"title":"ข้าวพร้อมกับ3อย่าง + เครื่องดื่ม 1 แก้ว GrabBox 🍱","description":"","imageSrc":"https://d1sag4ddilekf6.cloudfront.net/compressed_webp/items/THITE20230628103945076637/detail/183044736a6c4159bb4fc06ae08f0a7e_1687948785232576163.webp","price":"219"},{"title":"ข้าวพร้อมกับข้าว 2 อย่าง","description":"","imageSrc":"https://d1sag4ddilekf6.cloudfront.net/compressed_webp/items/THITE20211130075022059932/detail/1e131ff29c4e4ed8bce31b1c4d5abe8c_1638259893582058257.webp","price":"129"},{"title":"ข้าวพร้อมกับข้าว 3 อย่าง","description":"Rice with Menu 3 menus","imageSrc":"https://d1sag4ddilekf6.cloudfront.net/compressed_webp/items/THITE20220727071641029552/detail/00e6dc8f762f4f01ae8417ec82dc6609_1658906201269248402.webp","price":"199"},{"title":"VIP ชุดข้าวผัดน้ำพริกแซลมอนไข่นุ่ม + ขนมจีบกุ้ง + บัวลอยมันม่วง","description":"VIP Soft Omelet on Chilli Dip Fried Rice w/Grilled Salmon + Shrimp Roe Dimsum + Purple Sweet Potato Pearls in Coconut Cream","imageSrc":"https://d1sag4ddilekf6.cloudfront.net/compressed_webp/items/THITE20210531153651236099/detail/a9f6db11fa5c4b3ca08ac2d000ee214b_1661167200403947770.webp","price":"355"},{"title":"VIP ชุดข้าวหน้าไก่ย่างเทอริยากิ + บัวลอยมันม่วง","description":"VIP Chicken Teriyakai on Rice + Purple Sweet Potato Pearls in Coconut Cream","imageSrc":"https://d1sag4ddilekf6.cloudfront.net/compressed_webp/items/THITE20210531153650104982/detail/f56a00cbe48f45a3813f7ae08c2d069a_1661167200427463358.webp","price":"205"},{"title":"VIP เส้นจันท์ผัดไทยกุ้งสด+ปีกไก่ทอดสมุนไพร+สาคูถั่วดำมะพร้าวอ่อน","description":"VIP Fried Rice Vermicelli Thai Style w/ Prawns+Deep - Fried Chicken Wings+Sago & Black Bean in Coconut Cream","imageSrc":"https://d1sag4ddilekf6.cloudfront.net/compressed_webp/items/THITE20220420112936025914/detail/6514fb09e0ab410c89c097306fd0b868_1661167200407759630.webp","price":"275"},{"title":"VIP ข้าวแกงมัสมั่นไก่ไข่นุ่ม+ทอดมันปลาอินทรีย์+สาคูถั่วดำมะพร้าวอ่อน","description":"VIP Soft Omelet on Rice w/Chicken Massaman Curry+Deep Fried Organic Fish+Sago & Black Bean in Coconut Cream","imageSrc":"https://d1sag4ddilekf6.cloudfront.net/compressed_webp/items/THITE20220420112937013921/detail/405f5fa633a94a70a8555fa21f617e4f_1661167200401389764.webp","price":"265"},{"title":"VIP ข้าวหมูกระเทียมพริกไทย + ทอดมันปลาอินทรีย์ + เค้กกล้วยหอม","description":"VIP Rice w/ Garlic & Pepper Pork Slices and Deep Fried Organic Fish and Banana Cake","imageSrc":"https://d1sag4ddilekf6.cloudfront.net/compressed_webp/items/THITE20220420112937029203/detail/74c93bc2a82640d6bca7a1c60f452578_1661167200435021769.webp","price":"235"},{"title":"VIP ชุดสปาเก็ตตี้คาโบนาร่า + ไส้กรอกรวมรสย่าง + บัทเทอร์เค้ก","description":"VIP Spaghetti Carbonara + Sausage + Butter Cake","imageSrc":"https://d1sag4ddilekf6.cloudfront.net/compressed_webp/items/THITE20220420112937033422/detail/ae07c4eb9f7b4b12a8709cdec0c8cd17_1661167200476555796.webp","price":"235"},{"title":"VIP ชุดสปาเก็ตตี้โบโลเนสไก่ + ไส้กรอกรวมรสย่าง + บัทเทอร์เค้ก","description":"VIP Spaghetti Bolognese Chicken+ Sausage + Butter Cake","imageSrc":"https://d1sag4ddilekf6.cloudfront.net/compressed_webp/items/THITE20220420112937043519/detail/1d85c05bfa0b48578bc006d7d1504ef4_1661167200415631770.webp","price":"215"},{"title":"<โปรโมชัน> ชุดเซตคุกกี้เดลี่ S&P (กล่องกิ๊ฟเซต 4 กระปุก)","description":"พิเศษ! 235.- จากปกติ 275.- \n(คุ้กกี้ 4 กระปุก ราคาพิเศษ)","imageSrc":"https://d1sag4ddilekf6.cloudfront.net/compressed_webp/items/THITE20230810091931061045/detail/e03e4e6cb2d64c158ef99756692e4a33_1692273619691772781.webp","price":"235"},{"title":"<โปรโมชัน> น้ำส้มวาเลนเซีย(6กล่อง)","description":"พิเศษ! 95.- จากปกติ 114.- \n(น้ำผลไม้ UHT 6 กล่อง ราคาพิเศษ)","imageSrc":"https://d1sag4ddilekf6.cloudfront.net/compressed_webp/items/THITE20230810091931139570/detail/85ae35e9336c44c694146adbc307aa6a_1692273619855201227.webp","price":"95"},{"title":"<โปรโมชัน> น้ำแอปเปิ้ลผสมน้ำทับทิม(6กล่อง)","description":"พิเศษ! 95.- จากปกติ 114.- \n(น้ำผลไม้ UHT 6 กล่อง ราคาพิเศษ)","imageSrc":"https://d1sag4ddilekf6.cloudfront.net/compressed_webp/items/THITE20230810091931167030/detail/1bae01237f1a47bf8ef6ffec17ba9229_1692273619940933374.webp","price":"95"},{"title":"<โปรโมชัน> น้ำนมข้าวโพด(6กล่อง)","description":"พิเศษ! 95.- จากปกติ 114.- \n(น้ำผลไม้ UHT 6 กล่อง ราคาพิเศษ)","imageSrc":"https://d1sag4ddilekf6.cloudfront.net/compressed_webp/items/THITE20230810091931202668/detail/d0dc9f5e62a6474e850ed2e9bb3589d6_1692273619838871062.webp","price":"95"},{"title":"<โปรโมชัน> น้ำองุ่นแดง(6กล่อง)","description":"พิเศษ! 95.- จากปกติ 114.- \n(น้ำผลไม้ UHT 6 กล่อง ราคาพิเศษ)","imageSrc":"https://d1sag4ddilekf6.cloudfront.net/compressed_webp/items/THITE20230810091931247401/detail/98e9d06037514508afe9fc43a4721b67_1692273619946046166.webp","price":"95"},{"title":"<โปรโมชัน> ชุดเซตข้าวเกรียบ 2 กระป๋อง","description":"พิเศษ! 150.- จากปกติ 176.- \n(ชุดข้าวเกรียบ 2 กระป๋อง ราคาพิเศษ)","imageSrc":"https://d1sag4ddilekf6.cloudfront.net/compressed_webp/items/THITE20230810091931288387/detail/5d09146006974133b1a448c1ab82ba44_1692273619917830821.webp","price":"150"},{"title":"<โปรโมชัน> ชุดเซตทองม้วน 2 กล่อง","description":"พิเศษ! 200.- จากปกติ 250.- \n(ชุดทองม้วน 2 กล่อง ราคาพิเศษ)","imageSrc":"https://d1sag4ddilekf6.cloudfront.net/compressed_webp/items/THITE20230810091931346053/detail/2b680d045f944a3dabf3829fba31e091_1692273619931179867.webp","price":"200"},{"title":"<โปรโมชัน> ชุดเซตขนมขาไก่เนยสด 2 กระปุก","description":"พิเศษ! 108.- จากปกติ 136.- \n(ชุดขาไก่เนยสด 2 กระปุก ราคาพิเศษ)","imageSrc":"https://d1sag4ddilekf6.cloudfront.net/compressed_webp/items/THITE20230810091931394491/detail/c8ee31024ef949d5afcd2c584013d27e_1692273620233793505.webp","price":"108"},{"title":"<โปรโมชัน> ชุดเซตฟรุตพายสับปะรด 4 กล่อง","description":"พิเศษ! 200.- จากปกติ 232.- \n(ชุดฟรุตพายสับปะรด 4 กล่อง ราคาพิเศษ)","imageSrc":"https://d1sag4ddilekf6.cloudfront.net/compressed_webp/items/THITE20230810091932023639/detail/93ea166d45154d84bf8d61d1f37d7961_1692273620029908274.webp","price":"200"},{"title":"<โปรโมชัน> ชุดเซตพัฟเค้กสอดไส้ครีมกลิ่นส้ม 2 กล่อง","description":"พิเศษ! 100.- จากปกติ 110.- \n(ชุดพัฟเค้กสอดไส้ครีมกลิ่นส้ม 2 กล่อง ราคาพิเศษ)","imageSrc":"https://d1sag4ddilekf6.cloudfront.net/compressed_webp/items/THITE20230810091932181397/detail/6b5c321244624971a999f0d63798c363_1692273619843685029.webp","price":"100"},{"title":"<โปรโมชัน> ขนมจีบกุ้ง","description":"พิเศษ! 80.- จากปกติ 98.- \n(ขนมจีบกุ้ง 1 กล่อง ราคาพิเศษ)","imageSrc":"https://d1sag4ddilekf6.cloudfront.net/compressed_webp/items/THITE20230810091932211430/detail/f7716be2babf48759e9fcd5b003aebc0_1692273619849827528.webp","price":"80"},{"title":"<โปรโมชัน> ชุดเซตคุกกี้เดลี่ 2 กระปุก","description":"พิเศษ! 110.- จากปกติ 130.- (คุ้กกี้เดลี่ 2 กระปุก ราคาพิเศษ)","imageSrc":"https://d1sag4ddilekf6.cloudfront.net/compressed_webp/items/THITE20230831170036011463/detail/d69f69768c2e48c2a39a9b3d2bebc990_1693501236170096879.webp","price":"110"},{"title":"<โปรโมชัน> ขนมปังเนยสด 4 ชิ้น","description":"พิเศษ! 59.- จากปกติ 72.- (ขนมปังเนยสด 4 ชิ้น )","imageSrc":"https://d1sag4ddilekf6.cloudfront.net/compressed_webp/items/THITE20230831170036079285/detail/a9683935085e45058c9cd863ac405ef1_1693501236522399129.webp","price":"59"},{"title":"<โปรโมชัน> ครัวซองท์เนยสด 3 ชิ้น","description":"พิเศษ! 100.- จากปกติราคา 114.- ครัวซองท์เนยสด 3 ชิ้น","imageSrc":"https://d1sag4ddilekf6.cloudfront.net/compressed_webp/items/THITE20230831170036111586/detail/0b0b4e66cc114c57ac6332d8d4a652cf_1693501236812672566.webp","price":"100"},{"title":"<โปรโมชัน> เค้กนุ่ม 2 กล่อง (คละรสได้)","description":"เค้กนุ่ม 2 กล่อง (คละรสได้) \nพิเศษ! 200.- จากปกติ 250.-","imageSrc":"https://d1sag4ddilekf6.cloudfront.net/compressed_webp/items/THITE20230912052620039228/detail/f0720fa0b6404639a137a5e350621efc_1694767478211240048.webp","price":"200"},{"title":"<โปรโมชัน> คุกกี้ธัญพืช 1 กระปุก และ คุกกี้เดลี่ 1 กระปุก","description":"พิเศษ! 110.- จากปกติ 140.- \n(คุกกี้ธัญพืช 1 กระปุก \nและ คุกกี้เดลี่ 1 กระปุก\nราคาพิเศษ)","imageSrc":"https://d1sag4ddilekf6.cloudfront.net/compressed_webp/items/THITE20230912052620064498/detail/dc05cb46270d49f68687698ff22b07d2_1694767527218806455.webp","price":"110"},{"title":"<โปรโมชัน> ชุดเซตคุกกี้ผสมธัญพืช 2 กระปุก","description":"พิเศษ! 125.- จากปกติ 150.- \n(ชุดคุกกี้ธัญพืช 2 กระปุก ราคาพิเศษ)","imageSrc":"https://d1sag4ddilekf6.cloudfront.net/compressed_webp/items/THITE20230810091932082997/detail/8bc33ec2c80546d9808e31ab4b373e7f_1692273619718421518.webp","price":"125"},{"title":"<โปรโมชัน> ชุดพายกรอบแท่ง 2 กระปุก","description":"พิเศษ! 100.- จากปกติ 116.- \n(ชุดพายกรอบแท่ง 2 กระปุก ราคาพิเศษ)","imageSrc":"https://d1sag4ddilekf6.cloudfront.net/compressed_webp/items/THITE20230810091932141571/detail/7988d9e47e4242439e4886d901a83736_1692273619705438286.webp","price":"100"},{"title":"<โปรโมชัน> ขนมไหว้พระจันทร์ (ซื้อ 4 ชิ้น รับฟรี 1 ชิ้น)","description":"พิเศษ! 420.- \nจากปกติ 525.- \n(ซื้อขนมไหว้พระจันทร์ 4 ชิ้น รับฟรี 1 ชิ้น)","imageSrc":"https://d1sag4ddilekf6.cloudfront.net/compressed_webp/items/THITE20230731071628040521/detail/ae09d4df80b244c184ac9b18802e6d9d_1693205461375296894.webp","price":"420"},{"title":"<โปรโมชั่น> ชุดอาหารจานเดียวครบเครื่อง","description":"พิเศษ! จากปกติราคา 264.- (อาหารจานเดียว 1 เมนู + เครื่องดื่ม 1 เมนู)","imageSrc":"https://d1sag4ddilekf6.cloudfront.net/compressed_webp/items/THITE20230731071629079093/detail/1e7ac4aad4374c73bf21d96f5994a384_1690787789620600889.webp","price":"198"},{"title":"<โปรโมชัน> ชุดปลากะพงสุดคุ้ม (ลาบไก่ + ผัดแขนง)","description":"พิเศษ! จากปกติราคา 738.- (ปลากะพงทอด + ลาบไก่-มันทอดกรอบ + ผัดแขนงกะหล่ำน้ำมันหอย)","imageSrc":"https://d1sag4ddilekf6.cloudfront.net/compressed_webp/items/THITE20230531171150035164/detail/1a40b217a0e94ac49f07175f7f6aca1c_1690821020575611514.webp","price":"625"},{"title":"<โปรโมชัน> ลด35% ข้าวคลุกกะปิ+ข้าวผัดกุ้ง+น้ำ2","description":"ข้าวคลุกกะปิ + ข้าวผัดกุ้ง + ชา + กาแฟ","imageSrc":"https://d1sag4ddilekf6.cloudfront.net/compressed_webp/items/THITE20230423114545018833/detail/bc4febc00bfc49c29e7ef7e35dfca9f4_1684669638619963416.webp","price":"298"},{"title":"<โปรโมชัน> ลด30% ชุดอาหารจานเดียว 3 เมนู","description":"เลือก 3 จาก 5 (ข้าวหมูสไลซ์ทอดกระเทียมพริกไทยไข่นุ่ม / ข้าวคลุกกะปิ / ข้าวผัดกุ้ง / ข้าวหน้าไก่ราชวงศ์ / ข้าวผัดซาร์ดีน –ไข่ดาวกรอบ)","imageSrc":"https://d1sag4ddilekf6.cloudfront.net/compressed_webp/items/THITE20230521114951012876/detail/c349e94bb30146b89edd7272fedc5b0e_1692005641472725385.webp","price":"319"},{"title":"<โปรโมชัน> ชุดกับข้าวอร่อยคุ้ม","description":"พิเศษ! จากปกติราคา 445.-\n(แกงส้มชะอมกุ้งสด + ไข่ลูกสะใภ้ + ทอดมันปลาอินทรีย์)","imageSrc":"https://d1sag4ddilekf6.cloudfront.net/compressed_webp/items/THITE20230731071630027824/detail/329064f581ae42e7bdb515f82ae8e942_1690787790077224312.webp","price":"345"},{"title":"<โปรโมชัน> (ชุดอิสานสุดคุ้ม) ส้มตำไทย-ข้าวเหนียวคีนัว + เครื่องเคียง","description":"ชุดอาหารอีสาน ส้มตำไทย-ข้าวเหนียวคีนัว + เลือกเครื่องเคียงได้ตามใจ 1 รายการ","imageSrc":"https://d1sag4ddilekf6.cloudfront.net/compressed_webp/items/THITE20230628103945137355/detail/3fccf8b25db1409d91296c6ba757ebf8_1687948785542156936.webp","price":"199"},{"title":"<โปรโมชัน> (ชุดอิสานสุดคุ้ม) ลาบไก่-ข้าวเหนียวคีนัว + เครื่องเคียง","description":"ชุดอาหารอีสาน ลาบไก่-ข้าวเหนียวคีนัว + เลือกเครื่องเคียงได้ตามใจ 1 รายการ","imageSrc":"https://d1sag4ddilekf6.cloudfront.net/compressed_webp/items/THITE20230628103945179219/detail/728fa9bc4b4049f8bec7583c24d9b606_1687948785795418846.webp","price":"199"},{"title":"<โปรโมชัน> BlueCup ซื้อ 1 แถม 1 (เมนูปั่น แถม เย็น)","description":"พิเศษ จากปกติสูงสุดราคา 263.-","imageSrc":"https://d1sag4ddilekf6.cloudfront.net/compressed_webp/items/THITE20230423114546650313/detail/2db56ee74afb42ab861e2428f4a22961_1687948782516850175.webp","price":"158"},{"title":"<โปรโมชัน> ข้าวพร้อมกับข้าว 2 อย่าง (ซื้อ 5 ฟรี 1)","description":"","imageSrc":"https://d1sag4ddilekf6.cloudfront.net/compressed_webp/items/THITE20230315072021018821/detail/1f00f700e5834815b21555a1647d0a4b_1678865204382279774.webp","price":"645"},{"title":"<โปรโมชัน> เครื่องดื่ม RTD 3ขวด 100บาท","description":"","imageSrc":"https://d1sag4ddilekf6.cloudfront.net/compressed_webp/items/THITE20220408045006017101/detail/56826baf39d1413f95a6a1bba3d9fcd7_1649393388240723460.webp","price":"100"},{"title":"เค้กทริปเปิลเฟลเวอร์ 1 ปอนด์","description":"","imageSrc":"https://d1sag4ddilekf6.cloudfront.net/compressed_webp/items/THITE20230802144026013588/detail/2b3fc6f1f7414acdaba76533b52db319_1690987199516745126.webp","price":"435"},{"title":"กุ้งกระเบื้อง","description":"CRISPY PRAWN PANCAKE","imageSrc":"https://d1sag4ddilekf6.cloudfront.net/compressed_webp/items/THITE20230430140042011534/detail/a75c0e2c81064367a7ab2c258417a897_1682863242044657249.webp","price":"155"},{"title":"ข้าวตัง หน้าตั้ง","description":"RICE CRACKERS WITH MINCED PORK DIP","imageSrc":"https://d1sag4ddilekf6.cloudfront.net/compressed_webp/items/THITE20230430140042040564/detail/3fc9b60bbee4439582747af222320bc9_1682863242793025030.webp","price":"68"},{"title":"ข้าวตัง - แกงเขียวหวานไก่","description":"RICE CRACKERS W/CHICKEN GREEN CURRY","imageSrc":"https://d1sag4ddilekf6.cloudfront.net/compressed_webp/items/THITE20230430140043010643/detail/b310eabdbac54f51844a40279b90f5ae_1682863243055777493.webp","price":"125"},{"title":"ข้าวตัง - แกงเขียวหวานเนื้อน่อง","description":"RICE CRACKERS W/BRAISED BEEF GREEN CURRY","imageSrc":"https://d1sag4ddilekf6.cloudfront.net/compressed_webp/items/THITE20230430140043024500/detail/ca56465fa3b14434816afb67024a964c_1682863243293415435.webp","price":"155"},{"title":"ข้าวผัดป่าก์ไก่","description":"CHICKEN JUNGLE CURRY FRIED RICE","imageSrc":"https://d1sag4ddilekf6.cloudfront.net/compressed_webp/items/THITE20230430140044029351/detail/399642dc81eb4c0a80d294196ba0fda9_1682863244158114665.webp","price":"135"},{"title":"ข้าวมันส้มตำ แกงไก่-หมูฝอย","description":"COCONUT RICE W/ PAPAYA SALAD AND CHICKEN CURRY","imageSrc":"https://d1sag4ddilekf6.cloudfront.net/compressed_webp/items/THITE20230430140044041845/detail/367d134caddb4d72852e31bd5f4ffa89_1682863244439773622.webp","price":"178"},{"title":"ข้าวผัดแหนมทรงเครื่อง","description":"SOUR PORK SAUSAGE FRIED RICE","imageSrc":"https://d1sag4ddilekf6.cloudfront.net/compressed_webp/items/THITE20230430140044061125/detail/1fdb4dd18ec34a07a676da44eda8c1e2_1682863244675179821.webp","price":"135"},{"title":"ข้าวอบกุนเชียงไก่เม็ดมะม่วงหิมพานต์","description":"CHINESE SAUSAGE AND CHICKEN RICE POT","imageSrc":"https://d1sag4ddilekf6.cloudfront.net/compressed_webp/items/THITE20230430140044080757/detail/3bfc71f07103489c8861c0057fd808db_1686731000322075949.webp","price":"145"},{"title":"ข้าวแกงกะหรี่ไก่ทรงเครื่อง-อาจาด","description":"RICE - CHICKEN CURRY W/CUCUMBER RELISH","imageSrc":"https://d1sag4ddilekf6.cloudfront.net/compressed_webp/items/THITE20230430140045022171/detail/6ad31359c66f47a8be46c7b4861a47e1_1682863245137243424.webp","price":"145"},{"title":"ข้าวหน้าไก่ราชวงศ์","description":"RICE W/CHICKEN WHITE SAUCE","imageSrc":"https://d1sag4ddilekf6.cloudfront.net/compressed_webp/items/THITE20230430140045053824/detail/29b2401b902c4c6ebf055c3ec902c808_1682863245321087204.webp","price":"138"},{"title":"ข้าวผัดซาร์ดีน –ไข่ดาวกรอบ","description":"SARDINE FRIED RICE - CRISPY EGG","imageSrc":"https://d1sag4ddilekf6.cloudfront.net/compressed_webp/items/THITE20230430140045085305/detail/c8ff7e6c58cc4f3a8f757ee996c164a2_1682863245538571896.webp","price":"135"},{"title":"ข้าวผัดปู-ไข่ดาวกรอบ","description":"CRABMEAT FRIED RICE & CRISPY EGG","imageSrc":"https://d1sag4ddilekf6.cloudfront.net/compressed_webp/items/THITE20230430140045125455/detail/cbedf3c46e64497ca7ac70227c71bb1d_1682863245793046119.webp","price":"178"},{"title":"ข้าวหน้ากุ้งผัดพริกขี้หนู","description":"RICE W/CHILLI & GARLIC PRAWN CUBES","imageSrc":"https://d1sag4ddilekf6.cloudfront.net/compressed_webp/items/THITE20230430140046012115/detail/c547434e68a641bbb66aeb426b705d96_1682863246005050777.webp","price":"138"},{"title":"ข้าว-สเต็กหมูราดซอส","description":"RICE W/PORK BURGER IN SAVOURY SAUCE","imageSrc":"https://d1sag4ddilekf6.cloudfront.net/compressed_webp/items/THITE20230430140046042690/detail/023ffc9b21004b518b51d516bfe0c8ee_1682863246220643578.webp","price":"138"},{"title":"ข้าวผัดเกาหลีเนื้อนิวซีแลนด์","description":"KOREAN FRIED RICE W/ N.Z. BEEF","imageSrc":"https://d1sag4ddilekf6.cloudfront.net/compressed_webp/items/THITE20230430140046096679/detail/0eaa59cd282f43f2b002cd9670c6d03f_1682863246485346895.webp","price":"155"},{"title":"ก๋วยเตี๋ยวไก่กะเพรากรอบ","description":"STIR-FRIED RICE NOODLE W/SPICY CHICKEN BASIL","imageSrc":"https://d1sag4ddilekf6.cloudfront.net/compressed_webp/items/THITE20230430140046132840/detail/e1814973627a4deca5192cbfd6e26068_1682863246763885458.webp","price":"135"},{"title":"ก๋วยเตี๋ยวเนื้อสับ","description":"RICE NOODLE W/MINCED N.Z. BEEF IN CURRY SAUCE","imageSrc":"https://d1sag4ddilekf6.cloudfront.net/compressed_webp/items/THITE20230430140047053142/detail/0e655a3c7b9347de8ca20dba6722dfac_1682863247515892461.webp","price":"155"},{"title":"ก๋วยเตี๋ยวกุ้งสับ","description":"RICE NOODLE W/MINCED PRAWN IN CURRY SAUCE","imageSrc":"https://d1sag4ddilekf6.cloudfront.net/compressed_webp/items/THITE20230430140047072973/detail/8eeb1b27d4114adb97d401ee91551619_1682863247746163151.webp","price":"155"},{"title":"เส้นหมี่กุ้งผัดพริกเผา","description":"RICE VERMICELLI W/ PRAWNS & GAI LAN","imageSrc":"https://d1sag4ddilekf6.cloudfront.net/compressed_webp/items/THITE20230430140048010495/detail/0140b8a7fa6f4ba6b1d87c354370911f_1682863248023865887.webp","price":"165"},{"title":"วุ้นเส้นผัดไทยกุ้งจัมโบ้","description":"FRIED GLASS NOODLE THAI STYLE W/PRAWNS","imageSrc":"https://d1sag4ddilekf6.cloudfront.net/compressed_webp/items/THITE20230430140048022761/detail/1603a07b67eb4d818b032d396beacdd2_1682863248285627674.webp","price":"165"},{"title":"สตูว์ไก่น้ำใส","description":"CHICKEN STEW CLEAR SOUP","imageSrc":"https://d1sag4ddilekf6.cloudfront.net/compressed_webp/items/THITE20230430140048054530/detail/d71dadaa30874e89970831cc995886bb_1682863248569657707.webp","price":"165"},{"title":"ทอดมันลูกชิ้นปลา","description":"FISH BALL & FRIED FISH PATTIES","imageSrc":"https://d1sag4ddilekf6.cloudfront.net/compressed_webp/items/THITE20230430140041017513/detail/78f2428f645144c2a91a6b412f2b14dc_1682863241799076477.webp","price":"135"},{"title":"โรตี แกงเขียวหวานไก่","description":"ROTI W/CHICKEN GREEN CURRY","imageSrc":"https://d1sag4ddilekf6.cloudfront.net/compressed_webp/items/THITE20230430140043044286/detail/2a9372027cd348018d706d02ae664262_1682863243678088389.webp","price":"138"},{"title":"โรตี แกงเขียวหวานเนื้อน่อง","description":"ROTI W/BRAISED BEEF GREEN CURRY","imageSrc":"https://d1sag4ddilekf6.cloudfront.net/compressed_webp/items/THITE20230430140043069883/detail/6af8ddbd77004459b35c64345d4531eb_1682863243924602326.webp","price":"168"},{"title":"ขนมจีน-แกงเขียวหวานไก่","description":"RICE SPAGHETTI W/CHICKEN GREEN CURRY","imageSrc":"https://d1sag4ddilekf6.cloudfront.net/compressed_webp/items/THITE20230430140047018194/detail/bd0f4cb21bd744cb9b12f78fde59d377_1682863247043842432.webp","price":"138"},{"title":"ขนมจีน-แกงเขียวหวานเนื้อน่อง","description":"RICE SPAGHETTI W/BRAISED BEEF GREEN CURRY","imageSrc":"https://d1sag4ddilekf6.cloudfront.net/compressed_webp/items/THITE20230430140047031318/detail/0fb6fb11063a4eddae9e7339eac982e8_1682863247235762071.webp","price":"168"},{"title":"ข้าวผัดอเมริกัน","description":"American Fried Rice","imageSrc":"https://d1sag4ddilekf6.cloudfront.net/compressed_webp/items/THITE20220331101226077764/detail/1ef37034cec94f0bbb1f8f2506bf3032_1648721546463390822.webp","price":"185"},{"title":"ข้าวคลุกกะปิ","description":"Shrimp-Paste Fried Rice & Condiments","imageSrc":"https://d1sag4ddilekf6.cloudfront.net/compressed_webp/items/THITE20220331101227049729/detail/090502e2037c49069a1b099831925ba9_1648721547163698439.webp","price":"185"},{"title":"ข้าวไก่อบ S&P","description":"S&P Rice w/ Roast Chicken","imageSrc":"https://d1sag4ddilekf6.cloudfront.net/compressed_webp/items/THITE20220331101227115355/detail/0347156f4a494690b0feb230f92abbd9_1652167725720449922.webp","price":"205"},{"title":"เส้นจันท์ผัดไทยกุ้งสดจัมโบ้","description":"Fried Rice Vermicelli Thai Style w/ Jumbo Prawns","imageSrc":"https://d1sag4ddilekf6.cloudfront.net/compressed_webp/items/THITE20220331101227201048/detail/123e3e1993534b5b987286e2d5250752_1648721547928319071.webp","price":"175"},{"title":"ข้าวกุ้งผัดพริกขี้หนูไข่นุ่ม","description":"Soft Omelet on Rice w/ Garlic & Chilli Prawns","imageSrc":"https://d1sag4ddilekf6.cloudfront.net/compressed_webp/items/THITE20220331101228062437/detail/5beadc86e8f548b1b5c279bd64064819_1648721548280521697.webp","price":"175"},{"title":"กระเพาะปลาเนื้อปู","description":"Fish Maw w/ Crabmeat","imageSrc":"https://d1sag4ddilekf6.cloudfront.net/compressed_webp/items/THITE20220331101228115465/detail/7cf4351d448644678e2c4ac11520fff4_1683627120137727508.webp","price":"165"},{"title":"สปาเก็ตตี้คาโบนาร่า","description":"Spaghetti Carbonara","imageSrc":"https://d1sag4ddilekf6.cloudfront.net/compressed_webp/items/THITE20220331101229019871/detail/c1746a5ad5e4442aa3e01084a6813196_1648721549048266008.webp","price":"185"},{"title":"ข้าวหมูทอดกระเทียมพริกไทยไข่นุ่ม","description":"Soft Omelette on Rice w/ Garlic & Pepper Kurobuta Pork Slices","imageSrc":"https://d1sag4ddilekf6.cloudfront.net/compressed_webp/items/THITE20220331101229056354/detail/aaab9ec6a80b410887a68e58709d5c25_1683627120125398295.webp","price":"168"},{"title":"ข้าวไข่ฟู - แกงเหลืองยอดมะพร้าวปลากะพง","description":"Omelet on Rice-Seabass Yellow Curry w/ Young Coconut Shoot","imageSrc":"https://d1sag4ddilekf6.cloudfront.net/compressed_webp/items/THITE20220331101229073271/detail/699f76925af24a19acfd3663d0d2c38d_1682867131360846739.webp","price":"188"},{"title":"ข้าวต้มปลากะพง","description":"Seabass Rice Soup","imageSrc":"https://d1sag4ddilekf6.cloudfront.net/compressed_webp/items/THITE20220331101230023841/detail/6013bffff54e4b00bf8672aed6e1c123_1683627120148904311.webp","price":"165"},{"title":"ข้าวผัดปู","description":"Crabmeat Fried Rice","imageSrc":"https://d1sag4ddilekf6.cloudfront.net/compressed_webp/items/THITE20220331101230066611/detail/e413665b544041e68a5e4d60d97dda51_1652167726291104810.webp","price":"158"},{"title":"ข้าวผัดกุ้ง","description":"Prawns Fried Rice","imageSrc":"https://d1sag4ddilekf6.cloudfront.net/compressed_webp/items/THITE20220331101231024611/detail/f19d4dba8b944c7e8143bf492bbfd351_1648721551332364354.webp","price":"145"},{"title":"ข้าวแกงส้มผักรวมกุ้ง ไข่ฟู","description":"Rice - Hot & Sour Vegetable and Prawns - Fluffed Omelette","imageSrc":"https://d1sag4ddilekf6.cloudfront.net/compressed_webp/items/THITE20220331101232010901/detail/1aaa93ceb6074868b5c628918e6b4739_1648721552080496693.webp","price":"158"},{"title":"โจ๊กหมูทรงเครื่อง","description":"Kurobuta Minced Pork Congee","imageSrc":"https://d1sag4ddilekf6.cloudfront.net/compressed_webp/items/THITE20220331101232035988/detail/3899462d539a4a02840bc256c8d78cf3_1652167726769426851.webp","price":"128"},{"title":"ข้าวหน้าไก่ S&P","description":"S&P Rice w/ Chicken in Brown Sauce","imageSrc":"https://d1sag4ddilekf6.cloudfront.net/compressed_webp/items/THITE20220331101232054960/detail/8d51a243c7e6489492974c64d7abda48_1652167726948659908.webp","price":"138"},{"title":"ข้าวซอยน่องไก่","description":"Northern Style Curry Noodle w/ Chicken Drumstick","imageSrc":"https://d1sag4ddilekf6.cloudfront.net/compressed_webp/items/THITE20220331101233017722/detail/6f46ae04978b401587286bbe5f25d699_1652167727282408508.webp","price":"165"},{"title":"ข้าวไข่นุ่มผัดน้ำพริกแซลมอน","description":"Soft Omelet on Rice w/ Chilli Dip Grilled Salmon","imageSrc":"https://d1sag4ddilekf6.cloudfront.net/compressed_webp/items/THITE20220331101234013601/detail/862a41aa342f44c08f02b135908abc25_1648721554023553708.webp","price":"265"},{"title":"ข้าวผัดคีนัว-แซลมอนทอดซอสน้ำปลา","description":"Quinoa Fried Rice w/ Savoury Salmon","imageSrc":"https://d1sag4ddilekf6.cloudfront.net/compressed_webp/items/THITE20220331101230042380/detail/d8802423fcfc4ffcae9351f874a36e7a_1652167726019945848.webp","price":"285"},{"title":"มักกะโรนีผัดกุ้งจัมโบ้","description":"Stir Fried Macaroni & Jumbo Prawns","imageSrc":"https://d1sag4ddilekf6.cloudfront.net/compressed_webp/items/THITE20220331101233034383/detail/302c69eb51ca42b486f852cc08d2c048_1648721553349109895.webp","price":"158"},{"title":"ข้าวผัดหมูเค็ม-ส้มตำ","description":"Salted Pork Fried Rice w/ Papaya Salad","imageSrc":"https://d1sag4ddilekf6.cloudfront.net/compressed_webp/items/THITE20220331101233055509/detail/cbd2a6136950436fb081f9a092c710a2_1652167727401573459.webp","price":"158"},{"title":"เค้กฟลอร่าแฟนตาซี เลเยอร์วานิลลา 2 ปอนด์","description":"Flora Fantasy Cake Vanilla Layer Cake 2 Lbs.","imageSrc":"https://d1sag4ddilekf6.cloudfront.net/compressed_webp/items/THITE20221031113122054050/detail/c7323943316c40b7bb7e5a13ecb6c545_1667215882244351138.webp","price":"765"},{"title":"เค้กการ์เดนปาร์ตี้ บัทเทอร์วานิลลา 2 ปอนด์","description":"Garden Party Cake Butter Vanilla Cake 2 Lbs.","imageSrc":"https://d1sag4ddilekf6.cloudfront.net/compressed_webp/items/THITE20221031113122018967/detail/062cf1087e4942d1931253919a28689d_1667215882003257688.webp","price":"765"},{"title":"เค้กอร่อยรวมรส 8 รส 1 ปอนด์","description":"1คุกกี้แอนด์ครีมไวท์ช็อกโกแลต 2เค้กบัทเทอร์วานิลลา 3เค้กเลเยอร์ใบเตย 4เค้กแบล็คฟอเรสต์ 5เค้กช็อกโกแลตฟัดจ์ 6เค้กชิฟฟ่อนกาแฟ 7เค้กออเรนจ์เลเยอร์ 8ฮอกไกโดมิลด์เค้ก","imageSrc":"https://d1sag4ddilekf6.cloudfront.net/compressed_webp/items/THITE20230614153616011949/detail/d95e42c23dce421084aeb186290c58d6_1694766772500129790.webp","price":"465"},{"title":"คัลเลอร์ฟูลเค้ก 1 ปอนด์","description":"1.บลูเบอรี่โยเกร์ตดีไลท์ 2.ออเรนจ์ครีมชีส 3.ทริปเปิลช็อกโกแลต 4.ทอฟฟี่แมคคาดาเมีย 5.มัทฉะชาเขียว 6.บานาน่าเลิฟเวอร์ 7.มิกซ์เบอรี่ช็อกโกแลต 8.บัทเทอร์สก็อตบิสคอฟ","imageSrc":"https://d1sag4ddilekf6.cloudfront.net/compressed_webp/items/THITE20230628103944128330/detail/1cded675f25049e8978a030b32bdcf1e_1694766772214103153.webp","price":"465"},{"title":"บลูเบอรี่ครีมชีสพาย","description":"Blueberry Cream Cheese Pie","imageSrc":"https://d1sag4ddilekf6.cloudfront.net/compressed_webp/items/THITE20230203072701032759/detail/f51b096c1b8843ae890370c9b4154038_1675409221175464303.webp","price":"495"},{"title":"ฮอกไกโดมิลด์เค้ก 1 ปอนด์","description":"Hokkaido MILK Cake 1 Lb.","imageSrc":"https://d1sag4ddilekf6.cloudfront.net/compressed_webp/items/THITE20210531153647019721/detail/ed1156a4bc3542699b628826f7d1b53d_1624846117237646958.webp","price":"485"},{"title":"ข้าวผัดน้ำพริกกุ้งสดจัมโบ้","description":"Prawn Sweet Pork Fried Rice with Chilli Sauce","imageSrc":"https://d1sag4ddilekf6.cloudfront.net/compressed_webp/items/THITE20230509071833011111/detail/704e83e49a0249a7acdf2dd9fd61e5df_1683616713004414478.webp","price":"165"},{"title":"ก๋วยเตี๋ยวราดหน้าหมูสไลด์","description":"Rice Noodle w/ Pork Slices With Gravy","imageSrc":"https://d1sag4ddilekf6.cloudfront.net/compressed_webp/items/THITE20230509071833056730/detail/9fd1397bd2404bb6a612b59593eaa05a_1683616713833473429.webp","price":"165"},{"title":"ข้าวผัดหนำเลี๊ยบทรงเครื่อง","description":"Black Olive Fried Rice","imageSrc":"https://d1sag4ddilekf6.cloudfront.net/compressed_webp/items/THITE20230509071834020433/detail/0a71583894c541b7a0dda8329dfe60c9_1683617142806449739.webp","price":"148"},{"title":"ก๋วยเตี๋ยวราดหน้าเรือโป๊ะ","description":"Rice Noodle w/ Seafood & Vegetables","imageSrc":"https://d1sag4ddilekf6.cloudfront.net/compressed_webp/items/THITE20230509071834046795/detail/459fc01aebae4748bb0ceb6dd2a55e63_1683616714421852560.webp","price":"185"},{"title":"ข้าวคีนัว - คั่วกลิ้งหมู - ผักสด","description":"Quinoa Rice - Stir Fried Spicy Minced Pork - Fresh Vegetable","imageSrc":"https://d1sag4ddilekf6.cloudfront.net/compressed_webp/items/THITE20230509071834069039/detail/6c65e64d882e4d57a2311b95119a4d26_1683616714731543556.webp","price":"158"},{"title":"ข้าวผัดคะน้าปลาเค็ม","description":"Fried Rice w/ Salted Fish Kailaan & Chicken Cubes","imageSrc":"https://d1sag4ddilekf6.cloudfront.net/compressed_webp/items/THITE20230509071835013070/detail/f9227991019d456285362e461f94eca5_1683616715161836093.webp","price":"138"},{"title":"ข้าวสะตอกุ้งหมูสับไข่นุ่ม","description":"Soft Omelet on Rice w/ Stir - Fried Thai Flat Beans w/ Minced Pork & Prawn","imageSrc":"https://d1sag4ddilekf6.cloudfront.net/compressed_webp/items/THITE20230509071835041069/detail/f95f3c08cb934b4299a41ded8a11e847_1683616715603021098.webp","price":"175"},{"title":"ข้าวไข่นุ่ม - ต้มแซ่บซี่โครงหมู","description":"Soft Omelet on Rice w/ Spicy Pork Ribs Soup","imageSrc":"https://d1sag4ddilekf6.cloudfront.net/compressed_webp/items/THITE20230430140048076020/detail/df74e6f345c544a487422baab5715d33_1682863248954975609.webp","price":"178"},{"title":"ข้าวกะเพรากุ้งสับ - ไข่ดาวกรอบ","description":"Minced Prawn Holy Basil Rice - Crispy Fried Egg","imageSrc":"https://d1sag4ddilekf6.cloudfront.net/compressed_webp/items/THITE20230430140049023592/detail/e8acc623c89d462cb15c501314a7f11a_1682863249139291840.webp","price":"145"},{"title":"สปาเก็ตตี้เบคอนผัดพริกแห้ง","description":"Stir-Fried Spaghetti with Dried Chilli and Crispy Bacon","imageSrc":"https://d1sag4ddilekf6.cloudfront.net/compressed_webp/items/THITE20230430140049046225/detail/14f09c722cde4ce18c620d7d5aa7ff2a_1682863249348342234.webp","price":"155"},{"title":"ข้าวกะเพราเนื้อนิวซีแลนด์ไข่นุ่ม","description":"Soft Omelet on Rice w/ Spicy New Zealand Beef Basil","imageSrc":"https://d1sag4ddilekf6.cloudfront.net/compressed_webp/items/THITE20210831072821023631/detail/cceb5de23fd3440db0451dfaa501201d_1630394901078298795.webp","price":"188"},{"title":"ข้าวอบทะเล","description":"Seafood Rice Pot","imageSrc":"https://d1sag4ddilekf6.cloudfront.net/compressed_webp/items/THITE20210531153651178406/detail/7f1e64ba7c44403e98ccc769db4bc76b_1652167728047563878.webp","price":"175"},{"title":"ข้าวไข่ฟู - แกงคั่วปูใบชะพลู","description":"Omelet on Rice-Turmeric Crab Yellow Curry w/ Betelnut Leaves","imageSrc":"https://d1sag4ddilekf6.cloudfront.net/compressed_webp/items/THITE20210531153650315886/detail/27dc96afba794296b1c47179cc105814_1682867057187498192.webp","price":"275"},{"title":"ข้าวกะเพราไก่ไข่นุ่ม","description":"Soft Omelet on Rice w/ Spicy Chicken Basil","imageSrc":"https://d1sag4ddilekf6.cloudfront.net/compressed_webp/items/THITE20230228061655013519/detail/3ba5fc7be0e642a482486877d9a3c27e_1677565015223180913.webp","price":"148"},{"title":"ข้าวแกงเขียวหวานไก่","description":"Rice w/ Chicken Green Curry","imageSrc":"https://d1sag4ddilekf6.cloudfront.net/compressed_webp/items/THITE20210531153650166695/detail/fece9c929ed742359be6718f2ab506f3_1652167730366271559.webp","price":"138"},{"title":"ข้าวผัดคีนัวแซลมอนนึ่งมะนาว","description":"Quinoa Fried Rice w/ Steamed Salmon in Lime & Chilli Dressing","imageSrc":"https://d1sag4ddilekf6.cloudfront.net/compressed_webp/items/THITE20210531153647377142/detail/62f0fb04b5ee47af85baaed1ec82b454_1652167730582280045.webp","price":"275"},{"title":"ข้าวผัดคีนัว-ปลากะพงจัมโบ้นึ่งมะนาว","description":"Quinoa Fried Rice w/Steamed Jumbo Seabass in Lime & Chilli Dressing","imageSrc":"https://d1sag4ddilekf6.cloudfront.net/compressed_webp/items/THITE20210531153651066026/detail/96ba7ff2bf66444e949dc488ce57be43_1652167728541273707.webp","price":"258"},{"title":"ข้าวหน้าไก่ย่างเทอริยากิ","description":"Chicken Teriyakai on Rice","imageSrc":"https://d1sag4ddilekf6.cloudfront.net/compressed_webp/items/THITE20210531153649361052/detail/aaf516c7462149dcbc05dc0e24584435_1652167730997493932.webp","price":"165"},{"title":"สปาเก็ตตี้โบโลเนสไก่","description":"Spaghetti Bolognese Chicken","imageSrc":"https://d1sag4ddilekf6.cloudfront.net/compressed_webp/items/THITE20210531153648141520/detail/39e8ec1c00dd424db49e2cb6cd8715fa_1652167732098085770.webp","price":"155"},{"title":"สลัดไก่อบ","description":"Roast Chicken Salad","imageSrc":"https://d1sag4ddilekf6.cloudfront.net/compressed_webp/items/THITE20210531153648287981/detail/66645439a7cd408dbf6cda09b5ec5cf3_1683627120345430900.webp","price":"245"},{"title":"สลัดซีซ่า","description":"Caesar Salad","imageSrc":"https://d1sag4ddilekf6.cloudfront.net/compressed_webp/items/THITE20210531153649230974/detail/b4610480612d4b29a8c1ddd2333fe749_1683627120396749720.webp","price":"175"},{"title":"สลัดแซลมอนย่าง","description":"Grilled Salmon Salad","imageSrc":"https://d1sag4ddilekf6.cloudfront.net/compressed_webp/items/THITE20210531153646391066/detail/3d2b435268c641b6aa21597a333d2d45_1683627120132873692.webp","price":"265"},{"title":"ข้าวหน้าแซลมอนย่างซีอิ้ว","description":"Salmon Teriyaki on Rice","imageSrc":"https://d1sag4ddilekf6.cloudfront.net/compressed_webp/items/THITE20220510072853018433/detail/2b2cbd6b72564e93935b2ad7e9a2f404_1652167733146001675.webp","price":"265"},{"title":"สปาเก็ตตี้ขี้เมาทะเล","description":"Spicy Seafood Spaghetti","imageSrc":"https://d1sag4ddilekf6.cloudfront.net/compressed_webp/items/THITE20210531153650034274/detail/6087a179eb874def84c3e2c76a568efd_1686121604988462327.webp","price":"185"},{"title":"ข้าวคลุกกะปิ (ขนาดอิ่มอร่อยกำลังดี) @135.-","description":"Shrimp-Paste Fried Rice & Condiments @135.-","imageSrc":"https://d1sag4ddilekf6.cloudfront.net/compressed_webp/items/THITE20230208055344019027/detail/8534e83ca92d4ddf81abb5cfe2d8e1f0_1681123143393121063.webp","price":"135"},{"title":"ข้าวหน้ากุ้งผัดพริกขี้หนูไข่นุ่ม (ขนาดอิ่มอร่อยกำลังดี) @135.-","description":"","imageSrc":"https://d1sag4ddilekf6.cloudfront.net/compressed_webp/items/THITE20230531132801011494/detail/ea1f546cac7646508107850682a02092_1685560045211113215.webp","price":"135"},{"title":"ข้าวหมูทอดกระเทียมพริกไทยไข่นุ่ม (ขนาดอิ่มอร่อยกำลังดี) @135.-","description":"","imageSrc":"https://d1sag4ddilekf6.cloudfront.net/compressed_webp/items/THITE20230531132812013772/detail/36d77d9a304546a6b3cd2e90820b75e0_1685560045191421797.webp","price":"135"},{"title":"กระเพาะปลาเนื้อปู","description":"Fish Maw w/ Crabmeat","imageSrc":"https://d1sag4ddilekf6.cloudfront.net/compressed_webp/items/THITE20210531153648309524/detail/dff6be8246a44c44abe5c9e5efde24e9_1683627120113910687.webp","price":"165"},{"title":"ข้าวต้มปลากะพง","description":"Seabass Rice Soup","imageSrc":"https://d1sag4ddilekf6.cloudfront.net/compressed_webp/items/THITE20210531153647083885/detail/4af7ae67705140ac9a4fa85077785506_1683627120185450677.webp","price":"165"},{"title":"โจ๊กหมูทรงเครื่อง","description":"Kurobuta Minced Pork Congee","imageSrc":"https://d1sag4ddilekf6.cloudfront.net/compressed_webp/items/THITE20210531153647163074/detail/1746ba9ef7bc48cab672877432cc6fe7_1652167732453713024.webp","price":"128"},{"title":"ข้าวต้มกุ้ง","description":"Prawns Rice Soup","imageSrc":"https://d1sag4ddilekf6.cloudfront.net/compressed_webp/items/THITE20210531153646381388/detail/b6a2038fa39d47e2959cbf838186a315_1652167732687319821.webp","price":"145"},{"title":"แซนวิชแฮม","description":"Ham Sandwich","imageSrc":"https://d1sag4ddilekf6.cloudfront.net/compressed_webp/items/3-CZDCFCN2WE5KL2-CZDTETLURTCTRA/detail/44a2d80141ac419aaca7d38457f647da_1588218260737953640.webp","price":"58"},{"title":"แซนวิชทูน่า","description":"Tuna Sandwich","imageSrc":"https://d1sag4ddilekf6.cloudfront.net/compressed_webp/items/3-CZDCFCN2WE5KL2-CZDTETLUL362LT/detail/5e6efb6a5cdd408c8c1b5dea30b2de67_1588218270669351472.webp","price":"58"},{"title":"แซนวิชปูอัด","description":"Crab Stick Sandwich","imageSrc":"https://d1sag4ddilekf6.cloudfront.net/compressed_webp/items/3-CZDCFCN2WE5KL2-CZDTETLUNZL1GJ/detail/03104004486d477f8d7bc39ace34901f_1588218283407284928.webp","price":"58"},{"title":"เกี๊ยวกุ้งน้ำ","description":"Prawn Wonton Soup","imageSrc":"https://d1sag4ddilekf6.cloudfront.net/compressed_webp/items/THITE20210531153646407567/detail/bc14f21476144439b06d792f6f74c76b_1652167732909869757.webp","price":"138"},{"title":"วุ้นเส้นผัดไข่เค็ม","description":"Fried Glass Noodle with Salted Egg","imageSrc":"https://d1sag4ddilekf6.cloudfront.net/compressed_webp/items/THITE20230509071835069061/detail/3c0ce2c469e940df8ef94a80517ecdac_1683616715963055174.webp","price":"145"},{"title":"แกงปูใบชะพลู","description":"Turmeric Crab Yellow Curry w/ Betelnut Leaves","imageSrc":"https://d1sag4ddilekf6.cloudfront.net/compressed_webp/items/THITE20230509071836010979/detail/368abac88b374efd848e03e014aa6b4f_1683616716275164302.webp","price":"298"},{"title":"แกงเขียวหวานเนื้อน่องพริกขี้หนู","description":"Green Curry Beef","imageSrc":"https://d1sag4ddilekf6.cloudfront.net/compressed_webp/items/THITE20230509071836033694/detail/b7c0d86a95324b42a8ce4fc2f25a6b96_1683616716588914752.webp","price":"235"},{"title":"แกงเหลืองไหลบัวปลากะพง","description":"Southern-style yellow curry with lotus stem and seabass","imageSrc":"https://d1sag4ddilekf6.cloudfront.net/compressed_webp/items/THITE20230509071836053672/detail/8bc5177cc3a94958b97ee0b30fbb2657_1683616716900293568.webp","price":"125"},{"title":"แกงเหลืองยอดมะพร้าวปลากะพง","description":"Seabass Yellow Curry w/ Young Coconut Shoot","imageSrc":"https://d1sag4ddilekf6.cloudfront.net/compressed_webp/items/THITE20230509071837029948/detail/73498c8011cc4ca6abf09f5f04e1f7f1_1683616717276445968.webp","price":"235"},{"title":"ต้มมะระซี่โครงหมู","description":"Bitter Gourd Soup with Pork Ribs","imageSrc":"https://d1sag4ddilekf6.cloudfront.net/compressed_webp/items/THITE20230430140049062482/detail/e4f4751195f9400885ce4bae2edeafa9_1682863249638966948.webp","price":"175"},{"title":"ต้มแซ่บซี่โครงหมู","description":"Spicy Pork Ribs Soup","imageSrc":"https://d1sag4ddilekf6.cloudfront.net/compressed_webp/items/THITE20230430140049088951/detail/e412ff4b44f844ec9a05997ce72975a7_1682863249843190065.webp","price":"275"},{"title":"ผักแขนงกะหล่ำกุ้งสด","description":"Cabbage with fresh prawns","imageSrc":"https://d1sag4ddilekf6.cloudfront.net/compressed_webp/items/THITE20230430140050020947/detail/60572453d289457ea83789a547c7b71f_1682863250080843084.webp","price":"145"},{"title":"ผัดผักบุ้งไฟแดง","description":"Stir Fried Morning Glory","imageSrc":"https://d1sag4ddilekf6.cloudfront.net/compressed_webp/items/THITE20230430140050033909/detail/8081b646ca7c419f956cda6e1a38e1ad_1682863250265013785.webp","price":"125"},{"title":"ปลากะพงนึ่งซีอิ๊ว","description":"Steamed Seabass with Soy Sauce","imageSrc":"https://d1sag4ddilekf6.cloudfront.net/compressed_webp/items/THITE20230430140050055458/detail/28c8bcdd3f01446abc115c9f32558e94_1682863250473686368.webp","price":"485"},{"title":"กะหล่ำปลีผัดน้ำปลากุ้งแห้งกรอบ","description":"Stir - Fired Cabbage w/ Fish Sauce & Dried Shrimp","imageSrc":"https://d1sag4ddilekf6.cloudfront.net/compressed_webp/items/THITE20230430140050076332/detail/86a73ad7e5cc414f913dfda919f3b8ec_1682863250742403918.webp","price":"138"},{"title":"หมู-ไข่พะโล้","description":"Stewed egg - pork belly (Palo)","imageSrc":"https://d1sag4ddilekf6.cloudfront.net/compressed_webp/items/THITE20220103153810260885/detail/907455e7fd444f92b154efeecb1d250c_1648721507121035510.webp","price":"125"},{"title":"แกงเขียวหวานไก่","description":"Chicken Green Curry","imageSrc":"https://d1sag4ddilekf6.cloudfront.net/compressed_webp/items/THITE20210531153648370878/detail/45197902f007469caefa2a7161412c0b_1648721510762053002.webp","price":"148"},{"title":"ผักตุ๋นเห็ดหอม","description":"Vegetable Stew with Shiitake Mushroom","imageSrc":"https://d1sag4ddilekf6.cloudfront.net/compressed_webp/items/THITE20210531153647098887/detail/c49a43ebc91c421492a30408579a0621_1648721511514379037.webp","price":"138"},{"title":"ปีกไก่ตุ๋น","description":"Braised Chicken Wings Soup","imageSrc":"https://d1sag4ddilekf6.cloudfront.net/compressed_webp/items/THITE20210531153650085472/detail/202f1acb1300446881031713c7f9ed88_1648721512540763604.webp","price":"128"},{"title":"ข้าวกล้องงอก","description":"Gaba Rice","imageSrc":"https://d1sag4ddilekf6.cloudfront.net/compressed_webp/items/THITE20200416064633038196/detail/2ff5625e20fb4e2eac88da684576058d_1587019593473971488.webp","price":"25"},{"title":"ข้าวหอมมะลิ","description":"Jasmine Rice","imageSrc":"https://d1sag4ddilekf6.cloudfront.net/compressed_webp/items/THITE20200416064633023403/detail/121dad3200204bc0a0ec2092e95be305_1587019593261698175.webp","price":"15"},{"title":"ข้าวไรซ์เบอรี่","description":"Riceberry Rice","imageSrc":"https://d1sag4ddilekf6.cloudfront.net/compressed_webp/items/THITE20200416064633019065/detail/eddfe536a03b47e9991915bfd60bcdc3_1587019593029330899.webp","price":"25"},{"title":"ทอดมันปลาอินทรีย์","description":"Deep Fried Organic Fish","imageSrc":"https://d1sag4ddilekf6.cloudfront.net/compressed_webp/items/THITE20220228113054088316/detail/8ed9dc5898364d1ea1b104d2f0c158fd_1648721522478725008.webp","price":"98"},{"title":"หลนเต้าเจี้ยว+ผักจิ้ม","description":"Soybean flavour dip + vegetable","imageSrc":"https://d1sag4ddilekf6.cloudfront.net/compressed_webp/items/THITE20220228113054104371/detail/4e1d4f3b0d1a41359b4fc4e3f3cd0acd_1648721523030593941.webp","price":"98"},{"title":"คั่วกลิ้งหมู","description":"Stir Fried Spicy Minced Pork","imageSrc":"https://d1sag4ddilekf6.cloudfront.net/compressed_webp/items/THITE20220228113054130649/detail/c1d679dfbfb74f20a690e7a5348ab55e_1648721523351981487.webp","price":"98"},{"title":"ไก่ทอดกระเทียม","description":"Fried chicken with garlic and pepper","imageSrc":"https://d1sag4ddilekf6.cloudfront.net/compressed_webp/items/THITE20220228113054179055/detail/6f15da901b6141a194765ce69d669dfd_1648721524279965545.webp","price":"98"},{"title":"ลูกชิ้นปลาผัดพริกเหลืองหน่อไม้","description":"Stir-fried fish balls with chilli and bamboo shoot","imageSrc":"https://d1sag4ddilekf6.cloudfront.net/compressed_webp/items/THITE20220228113054196267/detail/22f0cc2cda3f49ddb238dc7ffdfa5c86_1648721525100242499.webp","price":"98"},{"title":"ไก่ผัดพริกขิงเห็ดหูหนู","description":"Stir-fried chicken with ginger and mushroom","imageSrc":"https://d1sag4ddilekf6.cloudfront.net/compressed_webp/items/THITE20220228113054204790/detail/820a24d408964ec79ae38b4c25f9b9a2_1648721525426724125.webp","price":"98"},{"title":"ฟักทองผัดไข่","description":"Stir-fried Pumpkin with Eggs","imageSrc":"https://d1sag4ddilekf6.cloudfront.net/compressed_webp/items/THITE20220228113054163320/detail/53dc88c200e9412fbcbc1b2fbb55a534_1648721523654066641.webp","price":"98"},{"title":"ปอเปี้ยะสด","description":"Fresh Spring Rolls","imageSrc":"https://d1sag4ddilekf6.cloudfront.net/compressed_webp/items/THITE20230208055309016310/detail/b833a3bb4fb648c687bf32078ce029b9_1675835573088100142.webp","price":"138"},{"title":"แกงเขียวหวานลูกชิ้นปลา","description":"Fish Balls Green Curry","imageSrc":"https://d1sag4ddilekf6.cloudfront.net/compressed_webp/items/THITE20220103153810202741/detail/5d0aefbb4d6c421e82115801d0153c2e_1648721506838782625.webp","price":"120"},{"title":"ปลากะพงทอดราดพริก","description":"Deep fried fish with chilli sauce","imageSrc":"https://d1sag4ddilekf6.cloudfront.net/compressed_webp/items/THITE20220103153810065038/detail/96564e0e4b6d49f0b5f93c0e0d48dcbc_1648721505160654316.webp","price":"175"},{"title":"ปลากะพงทอดซอส 3 รส","description":"Deep fried fish with 3 flavors sauce","imageSrc":"https://d1sag4ddilekf6.cloudfront.net/compressed_webp/items/THITE20220407050237018934/detail/501ba366fdd545c58b83ce6fcce002f1_1649307749756889802.webp","price":"485"},{"title":"ปลากะพงทอดซอสน้ำปลา","description":"Deep–Fried Seabass in Savoury Fish Sauce","imageSrc":"https://d1sag4ddilekf6.cloudfront.net/compressed_webp/items/THITE20210531153649403603/detail/45b599330a8b488cb0d86e110a45c72c_1683627120193733280.webp","price":"485"},{"title":"หมูก้อนทอดกระเทียมพริกไทย","description":"Savoury pork balls w/ Garlic & Pepper","imageSrc":"https://d1sag4ddilekf6.cloudfront.net/compressed_webp/items/THITE20210930060144168574/detail/f0b554881fef49179c1b73670496186a_1648721506164682043.webp","price":"98"},{"title":"หมูปรุงรสทอด","description":"Fried Seasoned Pork","imageSrc":"https://d1sag4ddilekf6.cloudfront.net/compressed_webp/items/THITE20210930060144217408/detail/b51032d912794a2e835bb00e08281a0c_1648721505905976727.webp","price":"98"},{"title":"ไก่ผัดเผ็ดกะทิสด","description":"Stir Fried Spicy Chicken with Coconut Milk","imageSrc":"https://d1sag4ddilekf6.cloudfront.net/compressed_webp/items/THITE20210930060144112517/detail/b36c548493164fcd8496ce5b7ea306e8_1648721506388106761.webp","price":"98"},{"title":"แกงเผ็ดไก่มะเขือเปราะ","description":"Thai Red Curry with Chicken","imageSrc":"https://d1sag4ddilekf6.cloudfront.net/compressed_webp/items/THITE20211115060315050406/detail/98cd24aadb5d48999c4fa736075733b5_1648721505668612623.webp","price":"98"},{"title":"แกงคั่วสับปะรดกุ้ง","description":"Red curry Pineapple and shrimp","imageSrc":"https://d1sag4ddilekf6.cloudfront.net/compressed_webp/items/THITE20211115060315061492/detail/35cb95c3e39043e99270b42ef10cc793_1648721507360005171.webp","price":"120"},{"title":"หมูผัดพริกหยวกหอมใหญ่","description":"Stir Fried Pork with Green Peppers","imageSrc":"https://d1sag4ddilekf6.cloudfront.net/compressed_webp/items/THITE20211115060316010933/detail/18af7b30116f44c08df371749e93a290_1648721505407052584.webp","price":"98"},{"title":"แกงเผ็ดหมูใส่ฟักทอง","description":"Pork & Pumkin Curry","imageSrc":"https://d1sag4ddilekf6.cloudfront.net/compressed_webp/items/THITE20211104103522206715/detail/a47361db71354a6aa44a99ec30fc0da3_1636956200506558389.webp","price":"120"},{"title":"ต้มแซ่บไก่","description":"Hot and Sour Chicken","imageSrc":"https://d1sag4ddilekf6.cloudfront.net/compressed_webp/items/THITE20211130075021133007/detail/10be76346651420b9bfbaf0bf1488ed5_1648721507667136709.webp","price":"120"}]